spw_corrosion/__init__.py
spw_corrosion/corrosion.py
spw_corrosion/plotting_functions.py
spw_corrosion/wall_properties.py
spw_corrosion-0.1.5.dist-info/LICENSE.txt
spw_corrosion-0.1.5.dist-info/METADATA
spw_corrosion-0.1.5.dist-info/WHEEL
spw_corrosion-0.1.5.dist-info/top_level.txt
spw_corrosion-0.1.5.dist-info/RECORD
