Metadata-Version: 2.1
Name: spw-corrosion
Version: 0.1.5
Summary: Analysis of sheep pile wall probability of failure considering corrosion.
Author: Antonis Mavritsakis
Author-email: amavrits@gmail.com
License: MIT
Requires-Python: >=3.9.0
License-File: LICENSE.txt
Requires-Dist: numpy ==1.26.4
Requires-Dist: scipy ==1.13.1
Requires-Dist: xarray ==2024.5.0
Provides-Extra: dev
